{
  "id": "hotboxroasters",
  "name": "Hotbox Roasters",
  "post": 714,
  "byfollow": 11700,
  "follow": 772,
  "intro": "||Specialty coffee crafted to meet your adventure needs|| #letshobox",
  "posts": [
    {
      "datetime": "2019-06-10T13:44:06.000Z",
      "article": "Morning HOTBOX rituals - #letshotbox",
      "tags": [
        "#letshotbox"
      ],
      "movie": [],
      "picture": [
        "https://scontent-nrt1-1.cdninstagram.com/vp/6ac1e2cccdbc2d7545d0570b5bd6b371/5D7C7773/t51.2885-15/e35/s1080x1080/61739738_749553435440625_2420446728511979927_n.jpg?_nc_ht=scontent-nrt1-1.cdninstagram.com"
      ],
      "contents_num": 1,
      "likes": 89,
      "views": -1
    },
    {
      "datetime": "2019-05-29T02:49:12.000Z",
      "article": "Load up your fridge with the one and only Hotbox Nitro Cold Brew Coffee - available on @wholefoods Prime Now in the Denver area 🤙🏼",
      "tags": [],
      "movie": [],
      "picture": [
        "https://scontent-nrt1-1.cdninstagram.com/vp/c52940714c6a4bd9865dff107fc929b4/5D851421/t51.2885-15/e35/60796075_709848732780376_8971131541798752020_n.jpg?_nc_ht=scontent-nrt1-1.cdninstagram.com"
      ],
      "contents_num": 1,
      "likes": 170,
      "views": -1
    },
    {
      "datetime": "2019-05-27T18:50:37.000Z",
      "article": "Good laughs after long hours of canning delicious nitro cold brew coffee - visit your local @wholefoods to get yours",
      "tags": [],
      "movie": [],
      "picture": [
        "https://scontent-nrt1-1.cdninstagram.com/vp/3edfea3ac64088fd883394384bd66ea3/5D9A85AE/t51.2885-15/e35/60013303_204191013888539_519745442149275654_n.jpg?_nc_ht=scontent-nrt1-1.cdninstagram.com"
      ],
      "contents_num": 1,
      "likes": 190,
      "views": -1
    },
    {
      "datetime": "2019-05-26T03:23:10.000Z",
      "article": "Start your holiday weekend mornings off right with a French Press of Bel-Air ☕️",
      "tags": [],
      "movie": [],
      "picture": [
        "https://scontent-nrt1-1.cdninstagram.com/vp/441442d17dfe4f90eb6f42e9a5469bbf/5D7FCD80/t51.2885-15/e35/60366715_411965366198134_6557371545385755990_n.jpg?_nc_ht=scontent-nrt1-1.cdninstagram.com"
      ],
      "contents_num": 1,
      "likes": 159,
      "views": -1
    },
    {
      "datetime": "2019-05-21T18:46:57.000Z",
      "article": "Best served chilled ❄️",
      "tags": [],
      "movie": [],
      "picture": [
        "https://scontent-nrt1-1.cdninstagram.com/vp/325b4b336b384fc1296bccbf8276c79d/5D81413D/t51.2885-15/e35/s1080x1080/61114382_427571894456866_502745112592826096_n.jpg?_nc_ht=scontent-nrt1-1.cdninstagram.com"
      ],
      "contents_num": 1,
      "likes": 151,
      "views": -1
    },
    {
      "datetime": "2019-05-14T15:29:43.000Z",
      "article": "Hotbox Cold Brew Coffee - craft coffee that goes where you do ⛰",
      "tags": [],
      "movie": [],
      "picture": [
        "https://scontent-nrt1-1.cdninstagram.com/vp/3dda3fbda3126cd5227ec65441c57e58/5D932D35/t51.2885-15/e35/s1080x1080/59866156_611796829225879_5234563549648245960_n.jpg?_nc_ht=scontent-nrt1-1.cdninstagram.com",
        "https://scontent-nrt1-1.cdninstagram.com/vp/7f059dcd18e6d2bdc62fa6490885d5cb/5D7D6DFF/t51.2885-15/e35/s1080x1080/60070334_164875837863753_5140330783221806942_n.jpg?_nc_ht=scontent-nrt1-1.cdninstagram.com"
      ],
      "contents_num": 2,
      "likes": 195,
      "views": -1
    },
    {
      "datetime": "2019-05-10T23:20:04.000Z",
      "article": "Hotbox Nitro Cold Brew Coffee for those sunny summer days 😎#letshotbox",
      "tags": [
        "#letshotbox"
      ],
      "movie": [],
      "picture": [
        "https://scontent-nrt1-1.cdninstagram.com/vp/b7cc55c860a1c6ce6098c0fa9d6fcbf2/5D88F6B5/t51.2885-15/e35/s1080x1080/59720666_398670524051330_7321656990958840828_n.jpg?_nc_ht=scontent-nrt1-1.cdninstagram.com"
      ],
      "contents_num": 1,
      "likes": 193,
      "views": -1
    },
    {
      "datetime": "2019-05-03T12:53:39.000Z",
      "article": "All the coffee love packed into a can! @hotboxroasters ☕️☕️☕️",
      "tags": [],
      "movie": [],
      "picture": [
        "https://scontent-nrt1-1.cdninstagram.com/vp/bf0bc5d14f5a13976a3e77d3943ffff9/5D8671E5/t51.2885-15/e35/57408273_2256822767905952_2360967354541704134_n.jpg?_nc_ht=scontent-nrt1-1.cdninstagram.com"
      ],
      "contents_num": 1,
      "likes": 184,
      "views": -1
    },
    {
      "datetime": "2019-04-27T14:57:23.000Z",
      "article": "Your daily dose of craft roasted coffee grounded to perfection and ready to kickstart your day 🚀",
      "tags": [],
      "movie": [],
      "picture": [
        "https://scontent-nrt1-1.cdninstagram.com/vp/83ae54177b759f3d7898de3aadde592a/5D7BF967/t51.2885-15/e35/57129735_2220080204974250_6281610276199971121_n.jpg?_nc_ht=scontent-nrt1-1.cdninstagram.com"
      ],
      "contents_num": 1,
      "likes": 233,
      "views": -1
    },
    {
      "datetime": "2019-04-24T14:02:44.000Z",
      "article": "One & done spiced rum barrel aged whole bean coffee - One Hit Wonder",
      "tags": [],
      "movie": [],
      "picture": [
        "https://scontent-nrt1-1.cdninstagram.com/vp/32a05989f36d58bb8323cdc411fe0bc5/5D8A7B88/t51.2885-15/e35/57213977_516631012076395_3460748111119431187_n.jpg?_nc_ht=scontent-nrt1-1.cdninstagram.com"
      ],
      "contents_num": 1,
      "likes": 194,
      "views": -1
    },
    {
      "datetime": "2019-04-24T00:44:38.000Z",
      "article": "Hotbox Canned Cold Brew - craft coffee can finally be everywhere you are",
      "tags": [],
      "movie": [],
      "picture": [
        "https://scontent-nrt1-1.cdninstagram.com/vp/c9dd73d95fa0c1e19211dcf16d3f82bd/5D9CF274/t51.2885-15/e35/57488165_164012604605197_8783117571995189300_n.jpg?_nc_ht=scontent-nrt1-1.cdninstagram.com"
      ],
      "contents_num": 1,
      "likes": 162,
      "views": -1
    },
    {
      "datetime": "2019-04-22T14:55:32.000Z",
      "article": "Keep the weekend going and start your day with a cup of Hotbox ☕️😋",
      "tags": [],
      "movie": [],
      "picture": [
        "https://scontent-nrt1-1.cdninstagram.com/vp/d661cbb8beffbb2c8b238b8e073b57cd/5D990F42/t51.2885-15/e35/56945095_649467888825163_6217513731197639061_n.jpg?_nc_ht=scontent-nrt1-1.cdninstagram.com"
      ],
      "contents_num": 1,
      "likes": 226,
      "views": -1
    },
    {
      "datetime": "2019-04-21T17:10:20.000Z",
      "article": "Happy Easter Hotbox Homies! Share some Soulshine with your favorite people today 🤗",
      "tags": [],
      "movie": [],
      "picture": [
        "https://scontent-nrt1-1.cdninstagram.com/vp/81a78a5057ea62cba2d8051b79b129e5/5D7B9A3A/t51.2885-15/e35/58410849_446876982751013_6120648414806198755_n.jpg?_nc_ht=scontent-nrt1-1.cdninstagram.com"
      ],
      "contents_num": 1,
      "likes": 146,
      "views": -1
    },
    {
      "datetime": "2019-04-20T18:01:38.000Z",
      "article": "One & done barrel aged hit! The 420 special run One Hit Wonder — get it now before its gone!",
      "tags": [],
      "movie": [],
      "picture": [
        "https://scontent-nrt1-1.cdninstagram.com/vp/dd956fb57afb83c7fb5c25ee41456db7/5D96F885/t51.2885-15/e35/57487944_146602013052787_8978794157665948634_n.jpg?_nc_ht=scontent-nrt1-1.cdninstagram.com"
      ],
      "contents_num": 1,
      "likes": 197,
      "views": -1
    },
    {
      "datetime": "2019-04-20T12:53:44.000Z",
      "article": "We like to do things other than just make badass cold brew…\n\nThis One Hit Wonder took shape in select spiced rum casks for 420-hours to highlight the coffee notes with an intoxicating aroma of rum drenched dried fruits and sun-dried flowers. **LIMITED SUPPLY ONLY** Per our master roaster, it’s recommended you enjoy this one hitter filtered or as a french press.\n\nUse code HOT420 at checkout today only to receive a special 420 price on this deliciousness!",
      "tags": [],
      "movie": [],
      "picture": [
        "https://scontent-nrt1-1.cdninstagram.com/vp/206e51230ee49e0aa7d3dc9ee038a691/5D910780/t51.2885-15/e35/56226294_1250737071770541_8799020921350942393_n.jpg?_nc_ht=scontent-nrt1-1.cdninstagram.com"
      ],
      "contents_num": 1,
      "likes": 226,
      "views": -1
    },
    {
      "datetime": "2019-04-20T03:48:44.000Z",
      "article": "Meticulously roasted and carefully ground to meet the needs of your on-the-go adventures 🤘🏼 would you explore with single dosed Hotbox adventure coffee bags?",
      "tags": [],
      "movie": [],
      "picture": [
        "https://scontent-nrt1-1.cdninstagram.com/vp/81bb5c7c88e3aba515db0c97b09090ef/5D85422B/t51.2885-15/e35/57111706_570462733452395_8908561829314174170_n.jpg?_nc_ht=scontent-nrt1-1.cdninstagram.com"
      ],
      "contents_num": 1,
      "likes": 264,
      "views": -1
    },
    {
      "datetime": "2019-04-19T01:58:19.000Z",
      "article": "Who said decaf couldn’t be specialty, our Moonshine Decaf is packed with flavor and makes for the perfect addition to any coffee spread! ***check out our latest story post for a little sneak peek on an upcoming special release blend, we promise you’ll like it! ***",
      "tags": [],
      "movie": [],
      "picture": [
        "https://scontent-nrt1-1.cdninstagram.com/vp/7692d4f048956af107fe15bfa1b8915a/5D83E517/t51.2885-15/e35/57506182_397682464161050_5475687893527477835_n.jpg?_nc_ht=scontent-nrt1-1.cdninstagram.com"
      ],
      "contents_num": 1,
      "likes": 178,
      "views": -1
    },
    {
      "datetime": "2019-04-17T23:09:34.000Z",
      "article": "A Whole Lotta Ground Coffee Greatness - Get yourself some deliciously smooth Whole Lotta Love whole bean coffee ... NOW!",
      "tags": [],
      "movie": [],
      "picture": [
        "https://scontent-nrt1-1.cdninstagram.com/vp/14630659f88f1f37d330c5d4f9d3e78a/5D7AEA7A/t51.2885-15/e35/57561453_641043466322333_5840148338611071089_n.jpg?_nc_ht=scontent-nrt1-1.cdninstagram.com"
      ],
      "contents_num": 1,
      "likes": 243,
      "views": -1
    },
    {
      "datetime": "2019-04-17T04:49:54.000Z",
      "article": "Hotbox Nitro Cold Brew - best served with a little extra shakin’",
      "tags": [],
      "movie": [],
      "picture": [
        "https://scontent-nrt1-1.cdninstagram.com/vp/0281d7f5d9bcf3577d574d8ff708b01e/5D9E234D/t51.2885-15/e35/56226311_127168901715234_2130455261818584009_n.jpg?_nc_ht=scontent-nrt1-1.cdninstagram.com"
      ],
      "contents_num": 1,
      "likes": 166,
      "views": -1
    }
  ]
}